{
  "label": "2019 Giro d'Italia Stage 3",
  "race_name": "Giro d'Italia",
  "race_date": "2019-05-13",
  "stage": 3,
  "video": {
    "video_id": "YmWHn8-j72g",
    "title": "Giro d’Italia 2019 | Stage 3 Highlights | Cycling | Eurosport",
    "url": "https://youtube.com/watch?v=YmWHn8-j72g",
    "channel": "playlist_import",
    "published": "2019-05-13T16:45:32Z",
    "match_score": 999
  },
  "transcript": {
    "snippet_count": 323,
    "raw_chars": 11238,
    "clean_chars": 11238,
    "duration_mins": 11.0,
    "clean_text": "And a very warm welcome to stage three of this 102nd Giro d'Italia. It's a first for Vinci, which has plenty of history. Of course, 500 years since the death of one of the most unique human beings in the world of human beings. Artist, scientist, and inventor Leonardo da Vinci came from there. Today, after 500 years of the place being talked about, it gets its first Giro d'Italia start. We went through briefly yesterday, and we're going to have a first-ever finish on the way to Orbetello after 220 km of racing. I say that, there's not much racing going on at the moment. 4 minutes and 26 seconds for our lone rider up the road, Sho Hatsuyama. He started the day 15 minutes and 41 seconds down on the overall general classification lead, that's still being held by Primož Roglič for a second successive day. 55 km into the stage. One climb out the way, but it wasn't classified. We're heading to Poggiobonzi next. That'll be the intermediate sprint. Few euros prize money as Sean Kelly was referring to for Sho Hatsuyama, our sole breakaway rider. And here he is. Poggiobonzi in the province of Siena. Jacopo Guarnieri will be the man who leads Arnaud Démare in towards this intermediate sprint. Points singled out. The former Dutch champion on the right-hand side peels off as we approach. It's Arnaud Démare who's going to go for the points, and nobody's going to challenge him. So, big points for Groupama-FDJ. Interesting, too, Sean, that behind him, couple of his teammates still there mopping up the other points as well. Yes. Well, none of the other teams or the sprinters got involved. So, yeah, the lead out for Démare, his teammates picking up in a level of the um big amount of points there as they go through, but yeah, that's the the question we were talking about yesterday and before this race kicked off on Saturday of the the big sprinters, who's going to be going for the Mario Cipollini at the end of this one because, you know, it is a very difficult final week in this race, the mountains we have to get over, and then there's the other races later on the season. Mario Cipollini has dropped quite a while. He's moving up on the left as we look at it now. Elia Viviani in the Italian national jersey doing just the same. Oh, this is going to be sprinters versus GC guys, and positioning is going to be so important. They are rocketing through the streets of Grosseto. Another turn. Bora-Hansgrohe holding the position well. Oh, and there's an intake of breath every time they take on those traffic islands. This is so, so nervy. Riders at the back. This is Thomas De Gendt staying well out of the way of everything at the back. Now then, we watch this on the right. Everyone watching each other coming up to this intermediate sprint now. Who's going to take it? There's that sleeping policeman out the way. Arnaud Démare on the right-hand side looks like he's going to go for it again. There is Démare. GC guys are probably wondering and watching seeing who's going to take them. Behind chasing, it's one of the riders from Bora-Hansgrohe who comes in second place. Arnaud Démare takes the points and the seconds, and after all that nervous energy, nothing. Nothing. It was a big build-up and I was expecting quite an interesting sprint there between the big sprinters here, but yeah, only Démare from the sprinters having a go there, but you know, everybody's nervous as you can see. They've been warned about this very, very technical going through the city here. Roundabouts everywhere, and you can see with the aerial shot here the problems caused. And the pink jersey, you could see he was very much at the fore, but when we came to the technical part, he got pushed back a lot, and he was back there in 30, maybe 40 position. That just tells us, you know, Roglic, the experience, he's not used to riding and fighting in this very technical section. And there he's getting bumped down, losing his teammates just to the right of that little sign that indicated that the traffic was going into the roundabout there. He lost about 10 positions in that little section there. A couple of his teammates further back and mamma mia, that was like an assault course going through Grosseto. 125 m to the top. A little bit of a movement here. Is anybody else close enough? Doesn't look it at all to me. 75, 50 25 and three points there go to Giulio Ciccone. Koen Bouwman coming over in second place. A little bit of a laugh from the other riders over behind. Oh, they made him suffer. They made him sweat there, but not work hard. Everybody's all together. One man was out in the break earlier on. Sho Hatsuyama was caught with 70 km to go. He was out there for 144 km on his own. 38 K average. As they pass through Montiano, when you look at the peloton here It doesn't look like they're going really fast, but when we see all the the the speed all there Oh, we've got riders caught behind. Riders caught behind and it looks like somebody might have been down there. On the right-hand side, we can see it. There's a Deceuninck-Quick Step rider just getting up. There's rider from UAE involved as well. That might have been Knox, I think. I'm not sure. We'll have to wait. That was certainly one of the more slight riders, I think, from Deceuninck-Quick Step. Number 85, it is him, James Knox. And it's outside three Ks to go. Two riders down as well from Katusha. Somebody involved from Ineos. Oh dear. OH, AND THERE ARE RIDERS GETTING CAUGHT ALL THE TIME as we turn left here. This is absolutely brutal. 1 and 1/2 km to the line and Fernando Gaviria looks in a great position at the back of this train of riders in white. To the right as we look at it, Arnaud Démare is there as well. 1.4 km to go. Elia Viviani, Sean, all the big sprinters are To to play their part. Yes, we can see Viviani is there. We can see as all the big sprinters there at the moment and yeah, Gaviria in a real good position, but still 1.2 km to go. Um, you know, you have to be able to hold that position. It can change a lot, but it's definitely going to be as one of these big sprints here and we can see here we're in the zone now where it's pretty open. The windy conditions doesn't look like there's a real real excitement at the moment because the you know, they're still you know, pretty much grouped together, but uh yes, it's going to be one one hectic final. One hectic finale coming up right now. We're inside 1 km to go and it's Bob Jungels for Deceuninck-Quick Step on the front. His teammate Elia Viviani, the Italian champion, waits at the back of a train of three more riders. Arnaud Démare, third from the front now with 600 m to go. On the left-hand side, you can see Dimension Data moving up and they're trying their best for Giacomo Nizzolo. Caleb Ewan trying to move up and follow the wheels as well. He's just put his face in the wind. Now with 500 m left to go, you can see it's a big effort trying to put Nizzolo in there. Renshaw sitting in front of him. This is the chicane, a very dangerous one at that. And look at the speed knocked off as they go around the corner. Well, Ackermann has won the fight for positioning there. He's on the wheel at the moment of Arnaud Démare who waits. It's slowed down. It speeds up again. 400 m remain. This is a very tricky finale. 350 to go. Viviani still in the middle. Ackermann as well, of course, in the purple jersey to look out for as well. A bit of elbow room as Moschetti is spotted. The Lotto is there AS WELL. NIZZOLO WAITS BUT AT THE FRONT IT'S ACKERMANN WHO GOES. ACKERMANN AT THE FRONT. THEY WAIT. CAN THEY GET AROUND HIM? THEY'VE GOT TO WAIT WITH THE HEADWIND BLOWING. ACKERMANN MIGHT HAVE GONE TOO EARLY. I THINK HE HAS. HE FADES. IT'S VIVIANI. VIVIANI, THE ITALIAN CHAMPION, GOT IT. HE WAITED. HE WAITED AND WHEN HE PUNCHED, THAT WAS IT. Elia Viviani wins stage three of the Giro d'Italia and it is chaos in Orbetello. Groups coming in behind. There's going to be time splits, but the headline on day three is that in the Italian national champion's jersey, Elia Viviani has done what he failed to do 24 hours previously. He waited. He followed the right wheel this time, and his timing was precise. Viviani, the winner in Orbetello on day three. This was an absolute killer, wasn't it? So, so dangerous there. It went left. It went right. And here, Ackermann is sort of he's a little lost, isn't he? Yes, well, I think a little bit too early and you know, the everybody is waiting a bit. They know this sprint, you know, to take it up too early is is you cannot do that. So, a little bit of looking around, but we can see Viviani here just into that chicane, you know, he he he he made up a few places and just in the right position, the right time in the wheel of Ackermann. A waiting, waiting, waiting. And when he went, it was the right time. Gaviria was coming as well, strong at the end. Nice to see. Congratulations straight away from Gaviria. He knew he was in the mix as well. It looked as though it was Viviani from Gaviria. Ackermann going very early into that headwind. Viviani leaving it to inside 100 m to go. Looks as though third on that occasion went to Demare, but we will get confirmation of that. Ackermann, who won yesterday, forced to go earlier today. And once he went, uh he was out of gas very quickly. Viviani in the green, white, and red. And the man in the white jersey with a red sleeves coming in just behind him. Guys, I'm just interrupting you quickly because we're hearing from on the ground that Elia Viviani has been disqualified for that sprint finish. So, let's have a look at this again and see exactly what that could have been about. This is the move that Brian was talking about uh across Moschetti and I did say that actually on the stage that he swerved from his line quite a lot. Certainly didn't expect the race jury to relegate anybody. No, he's the Italian national champion. That's a tough call. Nothing wrong here. It's further up when when he he gets on Ackermann's wheel here. Everything's going well. Caleb decides that he has to go now. Just looking on the left-hand side. Viviani decides to go with Ackermann instead of going with his lead out and Sabatini. But it's this acceleration just as he comes off Ackermann's wheel. Just watch this in a second here. It's round about now. He goes left. But he moves over left quite quickly. I can't see a lot in that, but that's a tough call that one in my opinion. really tough call. I mean we've seen disqualifications in that kind of a sprint before when we've had bodily contact, but Look at Moschetti afterwards. Moschetti, normally if you've been hard dealt with, you make a gesture afterwards, yeah. Yeah, but he's he's a young rider. You know you've made a mistake. Your teammate or your opponents let you know that you've done something wrong. Well, there it seemed that We don't know much about that. We're just waiting to hear whether this has been confirmed. The producer will tell me. Well, it has it has been confirmed that he's been disqualified. I mean Elia Viviani, usually a very emotional character. He he looks just sad rather than angry with that. So these are the new confirmed results and Fernando Gaviria is the stage winner from stage three.",
    "preview_start": "And a very warm welcome to stage three of this 102nd Giro d'Italia. It's a first for Vinci, which has plenty of history. Of course, 500 years since the death of one of the most unique human beings in the world of human beings. Artist, scientist, and inventor Leonardo da Vinci came from there. Today, after 500 years of the place being talked about, it gets its first Giro d'Italia start. We went through briefly yesterday, and we're going to have a first-ever finish on the way to Orbetello after 22",
    "preview_end": "istake. Your teammate or your opponents let you know that you've done something wrong. Well, there it seemed that We don't know much about that. We're just waiting to hear whether this has been confirmed. The producer will tell me. Well, it has it has been confirmed that he's been disqualified. I mean Elia Viviani, usually a very emotional character. He he looks just sad rather than angry with that. So these are the new confirmed results and Fernando Gaviria is the stage winner from stage three."
  },
  "status": "transcript_saved"
}