{
  "label": "2022 Bretagne Classic - Ouest-France",
  "race_name": "Bretagne Classic - Ouest-France",
  "race_date": "2022-08-28",
  "stage": null,
  "video": {
    "video_id": "nQlW6WIyOBY",
    "title": "Thrilling Finale In Brittany | Bretagne Classic Ouest-France 2022 Highlights",
    "url": "https://youtube.com/watch?v=nQlW6WIyOBY",
    "channel": "GCN Racing",
    "published": "2022-08-28 16:50:10+00:00",
    "match_score": 113.39,
    "all_candidates": [
      {
        "video_id": "nQlW6WIyOBY",
        "title": "Thrilling Finale In Brittany | Bretagne Classic Ouest-France 2022 Highlights",
        "channel": "GCN Racing",
        "published": "2022-08-28 16:50:10+00:00",
        "match_score": 113.39
      },
      {
        "video_id": "8_Ih5A26WLY",
        "title": "Lots Of Action On Punchy Circuit | Classic Lorient Agglomération - Trophée Ceratizit 2022 Highlights",
        "channel": "GCN Racing",
        "published": "2022-08-27 14:17:54+00:00",
        "match_score": 92.1
      },
      {
        "video_id": "tKWXlZ7zlIE",
        "title": "Will Late Attacks Deny The Sprinters? | BEMER Cyclassics 2022 Highlights",
        "channel": "GCN Racing",
        "published": "2022-08-21 16:02:29+00:00",
        "match_score": 56.29
      },
      {
        "video_id": "O5sI_Z4tLfI",
        "title": "Spring Classics Get Off To Flyer! | Omloop Het Nieuwsblad 2022 Men's Highlights",
        "channel": "GCN Racing",
        "published": "2022-02-26 16:59:18+00:00",
        "match_score": 43.21
      },
      {
        "video_id": "bvrABxfsrNU",
        "title": "Sprinters Return To Battle In Belgium | Classic Brugge - De Panne 2022 Men's Highlights",
        "channel": "GCN Racing",
        "published": "2022-03-23 17:40:19+00:00",
        "match_score": 42.9
      },
      {
        "video_id": "ueO8VGNlqVg",
        "title": "Team Dominance Over The Cobbles! | E3 Saxo Bank Classic Highlights 2022",
        "channel": "GCN Racing",
        "published": "2022-03-25 17:40:31+00:00",
        "match_score": 41.29
      },
      {
        "video_id": "kS9JOg0ZQLk",
        "title": "Sprinting Dominance In A Hectic Finale! | Classic Brugge - De Panne 2022 Women's Highlights",
        "channel": "GCN Racing",
        "published": "2022-03-24 17:11:40+00:00",
        "match_score": 12.9
      },
      {
        "video_id": "BjhnO3V-E1M",
        "title": "Chelsea v. Tottenham Hotspur (FULL MATCH) | 8/14/2022 | Premier League Classics | NBC Sports",
        "channel": "NBC Sports",
        "published": "2025-03-28 21:00:06+00:00",
        "match_score": -76.07
      }
    ]
  },
  "transcript": null,
  "status": "video_found"
}